<featureType>
  <id>FeatureTypeInfoImpl--158b7952:14c4be63ca3:433d</id>
  <name>drjscs_erp_l_av_adres</name>
  <nativeName>drjscs_erp_l_av_adres</nativeName>
  <namespace>
    <id>NamespaceInfoImpl--20f19466:136060abb97:-7bb9</id>
  </namespace>
  <title>DRJSCS  - RES - ERP de type L</title>
  <keywords>
    <string>drjscs_erp_l_av_adres</string>
    <string>features</string>
  </keywords>
  <nativeCRS class="projected">PROJCS[&quot;RGF93 / Lambert-93&quot;, 
  GEOGCS[&quot;RGF93&quot;, 
    DATUM[&quot;Reseau Geodesique Francais 1993&quot;, 
      SPHEROID[&quot;GRS 1980&quot;, 6378137.0, 298.257222101, AUTHORITY[&quot;EPSG&quot;,&quot;7019&quot;]], 
      TOWGS84[0.0, 0.0, 0.0, 0.0, 0.0, 0.0, 0.0], 
      AUTHORITY[&quot;EPSG&quot;,&quot;6171&quot;]], 
    PRIMEM[&quot;Greenwich&quot;, 0.0, AUTHORITY[&quot;EPSG&quot;,&quot;8901&quot;]], 
    UNIT[&quot;degree&quot;, 0.017453292519943295], 
    AXIS[&quot;Geodetic longitude&quot;, EAST], 
    AXIS[&quot;Geodetic latitude&quot;, NORTH], 
    AUTHORITY[&quot;EPSG&quot;,&quot;4171&quot;]], 
  PROJECTION[&quot;Lambert_Conformal_Conic_2SP&quot;, AUTHORITY[&quot;EPSG&quot;,&quot;9802&quot;]], 
  PARAMETER[&quot;central_meridian&quot;, 3.0], 
  PARAMETER[&quot;latitude_of_origin&quot;, 46.5], 
  PARAMETER[&quot;standard_parallel_1&quot;, 49.0], 
  PARAMETER[&quot;false_easting&quot;, 700000.0], 
  PARAMETER[&quot;false_northing&quot;, 6600000.0], 
  PARAMETER[&quot;scale_factor&quot;, 1.0], 
  PARAMETER[&quot;standard_parallel_2&quot;, 44.0], 
  UNIT[&quot;m&quot;, 1.0], 
  AXIS[&quot;Easting&quot;, EAST], 
  AXIS[&quot;Northing&quot;, NORTH], 
  AUTHORITY[&quot;EPSG&quot;,&quot;2154&quot;]]</nativeCRS>
  <srs>EPSG:2154</srs>
  <nativeBoundingBox>
    <minx>463605.34375</minx>
    <maxx>542003.5</maxx>
    <miny>6327890.5</miny>
    <maxy>6406994.0</maxy>
    <crs class="projected">EPSG:2154</crs>
  </nativeBoundingBox>
  <latLonBoundingBox>
    <minx>0.014154550890248</minx>
    <maxx>1.0288004637024404</maxx>
    <miny>44.01028887304781</miny>
    <maxy>44.744104244316205</maxy>
    <crs>GEOGCS[&quot;WGS84(DD)&quot;, 
  DATUM[&quot;WGS84&quot;, 
    SPHEROID[&quot;WGS84&quot;, 6378137.0, 298.257223563]], 
  PRIMEM[&quot;Greenwich&quot;, 0.0], 
  UNIT[&quot;degree&quot;, 0.017453292519943295], 
  AXIS[&quot;Geodetic longitude&quot;, EAST], 
  AXIS[&quot;Geodetic latitude&quot;, NORTH]]</crs>
  </latLonBoundingBox>
  <projectionPolicy>FORCE_DECLARED</projectionPolicy>
  <enabled>true</enabled>
  <advertised>true</advertised>
  <metadata>
    <entry key="cachingEnabled">false</entry>
  </metadata>
  <store class="dataStore">
    <id>DataStoreInfoImpl--20f19466:136060abb97:-7bb8</id>
  </store>
  <maxFeatures>0</maxFeatures>
  <numDecimals>0</numDecimals>
</featureType>