<layer>
  <name>dreal_tri_42_Lit_mineur_rivières_aggrege</name>
  <id>LayerInfoImpl-1381bef0:14d704a8e6f:62cd</id>
  <type>VECTOR</type>
  <defaultStyle>
    <id>StyleInfoImpl-1381bef0:14d704a8e6f:5a4e</id>
  </defaultStyle>
  <resource class="featureType">
    <id>FeatureTypeInfoImpl-1381bef0:14d704a8e6f:62cc</id>
  </resource>
  <enabled>true</enabled>
  <attribution>
    <title>DREAL</title>
    <href>http://www.aquitaine.developpement-durable.gouv.fr/</href>
    <logoURL>http://www.aquitaine.developpement-durable.gouv.fr/local/cache-vignettes/L102xH130/arton518-a3a7c.jpg</logoURL>
    <logoWidth>102</logoWidth>
    <logoHeight>130</logoHeight>
    <logoType>image/jpeg</logoType>
  </attribution>
</layer>