<layer>
  <name>srce_dalles_atlas</name>
  <id>LayerInfoImpl--4ffbdc12:1532c8efba5:7ed9</id>
  <type>VECTOR</type>
  <defaultStyle>
    <id>StyleInfoImpl--4ffbdc12:1532c9983a5:-7935</id>
  </defaultStyle>
  <resource class="featureType">
    <id>FeatureTypeInfoImpl--4ffbdc12:1532c8efba5:7ed8</id>
  </resource>
  <enabled>true</enabled>
  <attribution>
    <title>SRCE</title>
    <href>http://www.aquitaine.developpement-durable.gouv.fr/adoption-du-schema-regional-de-coherence-a2088.html</href>
    <logoURL>https://www.pigma.org/portail/sites/www.pigma.org.portail/files/sites/default/files/inline-images/pigma/les_partenaires/les_signataires_de_la_convention_pigma/autres/srce.jpg</logoURL>
    <logoWidth>178</logoWidth>
    <logoHeight>68</logoHeight>
    <logoType>image/jpeg</logoType>
  </attribution>
</layer>