<wmsStore>
  <id>WMSStoreInfoImpl--3cb9736d:1560848b5a6:-1ffe</id>
  <name>geoconcept_web_3</name>
  <description>geoconcept_web_3</description>
  <type>WMS</type>
  <enabled>true</enabled>
  <workspace>
    <id>WorkspaceInfoImpl-1a3b34e9:13a30459930:-7c33</id>
  </workspace>
  <metadata>
    <entry key="useConnectionPooling">true</entry>
  </metadata>
  <__default>false</__default>
  <capabilitiesURL>http://176.31.107.192:8888/geoconcept-web/wms</capabilitiesURL>
  <maxConnections>6</maxConnections>
  <readTimeout>60</readTimeout>
  <connectTimeout>30</connectTimeout>
</wmsStore>